htminify/__init__.py
htminify/htminify.py
htminify/wsgi.py
LICENSE
htminify-0.1.2.dist-info/LICENSE
htminify-0.1.2.dist-info/WHEEL
htminify-0.1.2.dist-info/METADATA
htminify-0.1.2.dist-info/RECORD
