Metadata-Version: 2.1
Name: htminify
Version: 0.1.2
Summary: A lightweight html minifier for all Python web frameworks and WSGI apps.
Home-page: https://github.com/AbhinavOmprakash/py-htminify
License: BSD-3-Clause
Keywords: html,django,flask,wsgi,middleware
Author: Abhinav Omprakash
Requires-Python: >=3.6,<4.0
Classifier: License :: OSI Approved :: BSD License
Classifier: Programming Language :: Python :: 3
Classifier: Programming Language :: Python :: 3.6
Classifier: Programming Language :: Python :: 3.7
Classifier: Programming Language :: Python :: 3.8
Classifier: Programming Language :: Python :: 3.9
Project-URL: Repository, https://github.com/AbhinavOmprakash/py-htminify
